pyXhWinClipTool.py
pyXhWinClipTool-0.0.4.dist-info/METADATA
pyXhWinClipTool-0.0.4.dist-info/WHEEL
pyXhWinClipTool-0.0.4.dist-info/entry_points.txt
pyXhWinClipTool-0.0.4.dist-info/top_level.txt
pyXhWinClipTool-0.0.4.dist-info/RECORD
