Metadata-Version: 2.1
Name: pyXhWinClipTool
Version: 0.0.4
Summary: python windows clip tools(calling native windows command
Home-page: https://github.com/xh-dev-py/pyXhWinClipTool
Author: xethhung
Author-email: pypi@xethh.dev
License: UNKNOWN
Platform: UNKNOWN
Provides-Extra: dev
Requires-Dist: pytest (>=3.7) ; extra == 'dev'
